[
	{
		"id": 1,
		"nameOfScript": "Новый скрипт",
		"title": "Добрый день! Вам удобно говорить?",
		"children": [
			{
				"id": 1,
				"title": "Добрый день! Вам удобно говорить?",
				"children": [
					{
						"id": 1,
						"title": "Да",
						"children": [
							{
								"id": 1,
								"title": "Я хотел бы предложить вам свои услуги!"
							}
						]
					},
					{
						"id": 2,
						"title": "Нет",
						"children": [
							{
								"id": 1,
								"title": "А когда удобно?"
							},
							{
								"id": 2,
								"title": "Могу я позвонить через час, наверное вы освободитесь?"
							}
						]
					}
				]
			}
		]
	},
	{
		"id": 2,
		"nameOfScript": "Еще один новый скрипт",
		"title": "Добрый день! Вам удобно говорить?",
		"children": [
			{
				"id": 1,
				"title": "Добрый день! Вам удобно говорить?",
				"children": [
					{
						"id": 1,
						"title": "Да",
						"children": [
							{
								"id": 1,
								"title": "Я хотел бы предложить вам свои услуги!"
							}
						]
					},
					{
						"id": 2,
						"title": "Нет",
						"children": [
							{
								"id": 1,
								"title": "А когда удобно?"
							}
						]
					}
				]
			}
		]
	},
	{
		"id": 3,
		"nameOfScript": "Еще один новый скрипт",
		"title": "Добрый день! Вам удобно говорить?",
		"children": [
			{
				"id": 1,
				"title": "Добрый день! Вам удобно говорить?",
				"children": [
					{
						"id": 1,
						"title": "Да",
						"children": [
							{
								"id": 1,
								"title": "Я хотел бы предложить вам свои услуги!"
							}
						]
					},
					{
						"id": 2,
						"title": "Нет",
						"children": [
							{
								"id": 1,
								"title": "А когда удобно?"
							}
						]
					}
				]
			}
		]
	}	
]
